jyj/__init__.py
jyj/utils.py
jyj-0.12.0.dist-info/METADATA
jyj-0.12.0.dist-info/WHEEL
jyj-0.12.0.dist-info/RECORD
