Metadata-Version: 2.1
Name: jyj
Version: 0.12.0
Summary: 
Author: Jiangyj.Tech
Author-email: Chief@Jiangyj.Tech
Requires-Python: >=3.12,<4.0
Classifier: Programming Language :: Python :: 3
Classifier: Programming Language :: Python :: 3.12
Requires-Dist: requests (>=2.32.3,<3.0.0)
